{
  "fileName": "etheria-restart.json",
  "title": "Etheria: Restart Tier List",
  "description": "",
  "heading": "Etheria: Restart Tier List",
  "introText": "",
  "datePublished": "2025-05-06",
  "dateModified": "2025-06-05",
	"langs": [
		"en"
	],
	"tiers": [
		{
			"name": "S Tier",
			"data": [
				{
					"itemName": "Lian",
					"itemDescription": "",
					"itemImage": "",
					"itemIcon": ""
				},
				{
					"itemName": "Massiah",
					"itemDescription": "",
					"itemImage": "",
					"itemIcon": ""
				},
				{
					"itemName": "Rosa",
					"itemDescription": "",
					"itemImage": "",
					"itemIcon": ""
				},
				{
					"itemName": "Rahu",
					"itemDescription": "",
					"itemImage": "",
					"itemIcon": ""
				},
				{
					"itemName": "Sania (Withered Shadow)",
					"itemDescription": "",
					"itemImage": "",
					"itemIcon": ""
				},
				{
					"itemName": "Freya",
					"itemDescription": "",
					"itemImage": "",
					"itemIcon": ""
				},
				{
					"itemName": "Lily",
					"itemDescription": "",
					"itemImage": "",
					"itemIcon": ""
				},
				{
					"itemName": "DokiDoki",
					"itemDescription": "",
					"itemImage": "",
					"itemIcon": ""
				},
				{
					"itemName": "Beyontin",
					"itemDescription": "",
					"itemImage": "",
					"itemIcon": ""
				},
				{
					"itemName": "Heinrich",
					"itemDescription": "",
					"itemImage": "",
					"itemIcon": ""
				},
				{
					"itemName": "Kloss",
					"itemDescription": "",
					"itemImage": "",
					"itemIcon": ""
				},
				{
					"itemName": "Dinah",
					"itemDescription": "",
					"itemImage": "",
					"itemIcon": ""
				},
				{
					"itemName": "Gray",
					"itemDescription": "",
					"itemImage": "",
					"itemIcon": ""
				},
				{
					"itemName": "Marvell",
					"itemDescription": "",
					"itemImage": "",
					"itemIcon": ""
				},
				{
					"itemName": "Helkid",
					"itemDescription": "",
					"itemImage": "",
					"itemIcon": ""
				},
				{
					"itemName": "Lingluo",
					"itemDescription": "",
					"itemImage": "",
					"itemIcon": ""
				},
				{
					"itemName": "Valerian",
					"itemDescription": "",
					"itemImage": "",
					"itemIcon": ""
				}
			]
		},
		{
			"name": "A Tier",
			"data": [
				{
					"itemName": "Xiada",
					"itemDescription": "",
					"itemImage": "",
					"itemIcon": ""
				},
				{
					"itemName": "Khloros",
					"itemDescription": "",
					"itemImage": "",
					"itemIcon": ""
				},
				{
					"itemName": "Diting",
					"itemDescription": "",
					"itemImage": "",
					"itemIcon": ""
				},
				{
					"itemName": "Fangus",
					"itemDescription": "",
					"itemImage": "",
					"itemIcon": ""
				},
				{
					"itemName": "Tsukiyo Mi",
					"itemDescription": "",
					"itemImage": "",
					"itemIcon": ""
				},
				{
					"itemName": "Chiaki (The Echo)",
					"itemDescription": "",
					"itemImage": "",
					"itemIcon": ""
				},
				{
					"itemName": "Kazuyo (The Reverie)",
					"itemDescription": "",
					"itemImage": "",
					"itemIcon": ""
				},
				{
					"itemName": "Veronika",
					"itemDescription": "",
					"itemImage": "",
					"itemIcon": ""
				},
				{
					"itemName": "Kraken",
					"itemDescription": "",
					"itemImage": "",
					"itemIcon": ""
				},
				{
					"itemName": "Obol",
					"itemDescription": "",
					"itemImage": "",
					"itemIcon": ""
				},
				{
					"itemName": "Viper",
					"itemDescription": "",
					"itemImage": "",
					"itemIcon": ""
				},
				{
					"itemName": "Mia",
					"itemDescription": "",
					"itemImage": "",
					"itemIcon": ""
				},
				{
					"itemName": "Sania",
					"itemDescription": "",
					"itemImage": "",
					"itemIcon": ""
				}
			]
		},
		{
			"name": "B Tier",
			"data": [
				{
					"itemName": "Rilmocha",
					"itemDescription": "",
					"itemImage": "",
					"itemIcon": ""
				},
				{
					"itemName": "Victor",
					"itemDescription": "",
					"itemImage": "",
					"itemIcon": ""
				},
				{
					"itemName": "Rin (The Unbowed)",
					"itemDescription": "",
					"itemImage": "",
					"itemIcon": ""
				},
				{
					"itemName": "Turandot",
					"itemDescription": "",
					"itemImage": "",
					"itemIcon": ""
				},
				{
					"itemName": "Yang",
					"itemDescription": "",
					"itemImage": "",
					"itemIcon": ""
				},
				{
					"itemName": "Celince",
					"itemDescription": "",
					"itemImage": "",
					"itemIcon": ""
				},
				{
					"itemName": "Cachi (The Guard)",
					"itemDescription": "",
					"itemImage": "",
					"itemIcon": ""
				},
				{
					"itemName": "Lilith",
					"itemDescription": "",
					"itemImage": "",
					"itemIcon": ""
				},
				{
					"itemName": "Chiaki",
					"itemDescription": "",
					"itemImage": "",
					"itemIcon": ""
				}
			]
		},
		{
			"name": "C Tier",
			"data": [
				{
					"itemName": "Tsutomu",
					"itemDescription": "",
					"itemImage": "",
					"itemIcon": ""
				},
				{
					"itemName": "Oboro",
					"itemDescription": "",
					"itemImage": "",
					"itemIcon": ""
				},
				{
					"itemName": "Andrew (Reason)",
					"itemDescription": "",
					"itemImage": "",
					"itemIcon": ""
				},
				{
					"itemName": "Dorothy (The Wisher)",
					"itemDescription": "",
					"itemImage": "",
					"itemIcon": ""
				},
				{
					"itemName": "No. 41",
					"itemDescription": "",
					"itemImage": "",
					"itemIcon": ""
				},
				{
					"itemName": "Kazami Kazuyo",
					"itemDescription": "",
					"itemImage": "",
					"itemIcon": ""
				},
				{
					"itemName": "RC-77",
					"itemDescription": "",
					"itemImage": "",
					"itemIcon": ""
				},
				{
					"itemName": "Dorothy",
					"itemDescription": "",
					"itemImage": "",
					"itemIcon": ""
				},
				{
					"itemName": "Rin",
					"itemDescription": "",
					"itemImage": "",
					"itemIcon": ""
				}
			]
		},
		{
			"name": "D Tier",
			"data": [
				{
					"itemName": "Andrew (Odd)",
					"itemDescription": "",
					"itemImage": "",
					"itemIcon": ""
				},
				{
					"itemName": "Sybil",
					"itemDescription": "",
					"itemImage": "",
					"itemIcon": ""
				},
				{
					"itemName": "Cachi",
					"itemDescription": "",
					"itemImage": "",
					"itemIcon": ""
				},
				{
					"itemName": "Asshu",
					"itemDescription": "",
					"itemImage": "",
					"itemIcon": ""
				},
				{
					"itemName": "Vice",
					"itemDescription": "",
					"itemImage": "",
					"itemIcon": ""
				}
			]
		}
	]
}